dialogstream/__init__.py
dialogstream/convert_file_path.py
dialogstream/extract_query_params.py
dialogstream/get_url_parts.py
dialogstream/main.py
dialogstream/match_filter.py
dialogstream/process.py
dialogstream/process_utils.py
dialogstream/router.py
dialogstream-1.4.8.dist-info/LICENSE
dialogstream-1.4.8.dist-info/METADATA
dialogstream-1.4.8.dist-info/WHEEL
dialogstream-1.4.8.dist-info/entry_points.txt
dialogstream-1.4.8.dist-info/top_level.txt
dialogstream-1.4.8.dist-info/RECORD
