Metadata-Version: 2.1
Name: dialogstream
Version: 1.4.8
Summary: A flexible stream routing and filtering system with support for scheduled tasks and event reactions
Home-page: https://github.com/pipexy/stream-filter-router
Author: Tom Sapletta
Author-email: info@softreck.dev
Classifier: Development Status :: 5 - Production/Stable
Classifier: Intended Audience :: Developers
Classifier: Topic :: Multimedia :: Video
Classifier: Topic :: System :: Systems Administration
Classifier: License :: OSI Approved :: Apache Software License
Classifier: Programming Language :: Python :: 3
Classifier: Programming Language :: Python :: 3.8
Classifier: Programming Language :: Python :: 3.9
Classifier: Programming Language :: Python :: 3.10
Classifier: Programming Language :: Python :: 3.11
Classifier: Operating System :: POSIX :: Linux
Requires-Python: >=3.8
License-File: LICENSE
Requires-Dist: pyyaml>=6.0
Requires-Dist: python-dotenv>=0.19.0
Requires-Dist: ffmpeg-python>=0.2.0
Requires-Dist: typing-extensions>=4.0.0
Requires-Dist: colorlog>=6.7.0
Requires-Dist: click>=8.0.0
Requires-Dist: prometheus-client>=0.19.0
Requires-Dist: fastapi>=0.104.1
Requires-Dist: uvicorn>=0.24.0
